more.jsonschema-0.2-py3.7-nspkg.pth
more/jsonschema/__init__.py
more/jsonschema/app.py
more/jsonschema/errors.py
more/jsonschema/loader.py
more/jsonschema/tests/test_jsonschema.py
more.jsonschema-0.2.dist-info/LICENSE.txt
more.jsonschema-0.2.dist-info/METADATA
more.jsonschema-0.2.dist-info/WHEEL
more.jsonschema-0.2.dist-info/namespace_packages.txt
more.jsonschema-0.2.dist-info/top_level.txt
more.jsonschema-0.2.dist-info/RECORD
