Metadata-Version: 2.1
Name: more.jsonschema
Version: 0.2
Summary: JSON Schema support for Morepath
Home-page: https://github.com/morepath/more.jsonschema
Author: Henri Hulski
Author-email: henri.hulski@gazeta.pl
License: BSD
Keywords: morepath validation
Platform: UNKNOWN
Classifier: Intended Audience :: Developers
Classifier: License :: OSI Approved :: BSD License
Classifier: Programming Language :: Python :: 3.6
Classifier: Programming Language :: Python :: 3.7
Classifier: Programming Language :: Python :: 3.8
Classifier: Programming Language :: Python :: Implementation :: PyPy
Requires-Dist: morepath (>=0.19)
Requires-Dist: jsonschema (>=3.2.0)
Provides-Extra: coverage
Requires-Dist: pytest-cov ; extra == 'coverage'
Provides-Extra: pep8
Requires-Dist: flake8 ; extra == 'pep8'
Requires-Dist: black ; extra == 'pep8'
Provides-Extra: test
Requires-Dist: pytest (>=2.9.1) ; extra == 'test'
Requires-Dist: pytest-remove-stale-bytecode ; extra == 'test'
Requires-Dist: webtest ; extra == 'test'
